{"id": "live_parallel_multiple_0-0-0", "ground_truth": [{"ChaFod": {"foodItem": ["Caesar salad"], "newIngredients": [""], "removeIngredients": ["anchovies", "anchovy"], "specialInstructions": [""]}}, {"ChaDri.change_drink": {"drink_id": ["123"], "new_preferences": [{"size": ["large"], "temperature": ["hot"], "sweetness_level": ["", "regular"], "milk_type": ["almond"], "special_instructions": [""]}]}}]}
{"id": "live_parallel_multiple_3-2-1", "ground_truth": [{"OpenWeatherMap.get_current_weather": {"location": ["Seoul, South Korea"], "units": ["", "metric"], "api_key": ["", "YOUR_API_KEY_HERE"]}}, {"ControlAppliance.execute": {"command": ["거실, 에어컨, 실행"]}}, {"HNA_WQA.search": {"keyword": ["Imjin War", "the Imjin War"], "result_format": ["", "text"], "language": ["", "EN"], "max_results": ["", 10]}}]}
{"id": "live_parallel_multiple_20-17-0", "ground_truth": [{"Buses_3_FindBus": {"from_city": ["Boston, MA"], "to_city": ["New York, NY"], "departure_date": ["2023-05-21"], "num_passengers": [2], "category": ["", "direct"]}}, {"Events_3_FindEvents": {"event_type": ["Music"], "city": ["New York, NY"], "date": ["2023-05-21"]}}]}
